{
  "user_question": "Which Fall Out Boy album was released on February 6, 2007 but leaked on the Internet the month before?",
  "final_answer": "Thought: It seems that Infinity on High did indeed leak on the Internet before its release. I have the answer.\nFinal Answer: Infinity on High",
  "steps": [
    {
      "content": "Which Fall Out Boy album was released on February 6, 2007 but leaked on the Internet the month before?",
      "id": "a317e912-23dc-4314-a23b-c3d7d342b28c",
      "type": "human",
      "additional_kwargs": {}
    },
    {
      "content": "Thought: I need to find the Fall Out Boy album that was released on February 6, 2007, but leaked on the Internet the month before.\nAction: search[Fall Out Boy album released on February 6, 2007]",
      "id": "4705fc3b-e80c-4401-bc91-d2a5fdff1d6a",
      "type": "agent",
      "additional_kwargs": {}
    },
    {
      "content": "Observation: Infinity on High - Infinity on High is the third studio album by American rock band Fall Out Boy, released on February 6, 2007, by Island Records.",
      "id": "83f28b8d-38f9-4767-bc89-550b99974a8a",
      "type": "human",
      "additional_kwargs": {}
    },
    {
      "content": "Thought: The album released on February 6, 2007, is Infinity on High. Now I need to find out if it leaked on the Internet the month before.\nAction: search[Infinity on High leaked on the Internet before release]",
      "id": "dffbee8b-1934-40a6-b672-17c4e2482c52",
      "type": "agent",
      "additional_kwargs": {}
    },
    {
      "content": "Observation: 22 janv. 2007 \u2014 Fall Out Boy have spoken out about new album 'Infinity On High' leaking on the internet. ... before. \u201c But he pleaded with fans to think about ...",
      "id": "3253c058-7c5e-4229-8a12-f9a5ee3333cd",
      "type": "human",
      "additional_kwargs": {}
    },
    {
      "content": "Thought: It seems that Infinity on High did indeed leak on the Internet before its release. I have the answer.\nFinal Answer: Infinity on High",
      "id": "67c1f3bb-0043-47ce-9868-d8375c645b42",
      "type": "agent",
      "additional_kwargs": {}
    }
  ],
  "tools_used": [],
  "errors": [],
  "agents_called": [
    "user",
    "gpt"
  ],
  "agent_actions": [
    "Action: search[Fall Out Boy album released on February 6, 2007]",
    "Think/Plan",
    "Action: search[Infinity on High leaked on the Internet before release]",
    "Think/Plan",
    "Think/Plan"
  ]
}